[
    {
        "title": "Home",
        "route": "#/home"
    },
    {
        "title": "Product",
        "route": "#/product",
        "submenu": [
            {
                "title": "Biscute",
                "route": "#/product/biscute"
            },
            {
                "title": "Chips",
                "route": "#/product/chips"
            }
        ]
    },
    {
        "title": "About",
        "route": "#/about"
    },
    {
        "title": "Privacy Policy",
        "route": "#/policy"
    },
    {
        "title": "Contact",
        "route": "#/contact"
    }
]